sssimp/__init__.py
sssimp/__main__.py
sssimp/config.py
sssimp/filters.py
sssimp/utils.py
sssimp/generators/css.py
sssimp/generators/data.py
sssimp/generators/html.py
sssimp/generators/jinja.py
sssimp/generators/markdown.py
sssimp-0.1.4.dist-info/LICENSE
sssimp-0.1.4.dist-info/METADATA
sssimp-0.1.4.dist-info/WHEEL
sssimp-0.1.4.dist-info/entry_points.txt
sssimp-0.1.4.dist-info/top_level.txt
sssimp-0.1.4.dist-info/RECORD
