Metadata-Version: 2.1
Name: sssimp
Version: 0.1.4
Summary: The Static Site Solution In Modern Python
License-File: LICENSE
Requires-Dist: jinja2
Requires-Dist: markdown
Requires-Dist: pymdown-extensions
Requires-Dist: pyyaml
